console_singleton.py
exceptions.py
audiobook/__init__.py
audiobook/assembly.py
audiobook/chapters.py
audiobook/controller.py
audiobook/cover.py
audiobook/language.py
audiobook/models.py
audiobook/mp4chapters.py
audiobook/preprocess.py
audiobook/renderer.py
audiobook/state.py
audiobook/tts.py
audiobook/voices.py
cli/__init__.py
cli/core.py
cli/errors.py
cli/main.py
cli/commands/__init__.py
cli/commands/audiobook.py
cli/commands/config.py
cli/commands/export.py
cli/commands/extract.py
cli/commands/format.py
cli/commands/pipeline.py
cli/commands/resume.py
cli/commands/translate.py
cli/debug/__init__.py
cli/debug/commands.py
config/__init__.py
config/loader.py
config/models.py
config/templates.py
config/workspace.py
debug_tools/__init__.py
debug_tools/analysis.py
debug_tools/common.py
debug_tools/extraction_summary.py
debug_tools/files.py
debug_tools/inspect.py
debug_tools/pending.py
debug_tools/preview.py
debug_tools/skip_lists.py
epub_io/__init__.py
epub_io/path_utils.py
epub_io/reader.py
epub_io/resources.py
epub_io/selector.py
epub_io/toc_utils.py
epub_io/writer.py
extraction/__init__.py
extraction/cleaners.py
extraction/epub_export.py
extraction/image_export.py
extraction/markdown_export.py
extraction/pipeline.py
extraction/segments.py
injection/__init__.py
injection/engine.py
injection/html_ops.py
logging_utils/__init__.py
logging_utils/logger.py
state/__init__.py
state/base.py
state/models.py
state/resume.py
state/store.py
translation/__init__.py
translation/controller.py
translation/languages.py
translation/polish.py
translation/prefilter.py
translation/prompt_builder.py
translation/refusal_filter.py
translation/providers/__init__.py
translation/providers/anthropic.py
translation/providers/base.py
translation/providers/deepl.py
translation/providers/gemini.py
translation/providers/grok.py
translation/providers/ollama.py
translation/providers/openai.py
web_templates/__init__.py
web_templates/index.html
web_templates/assets/css/app.css
tepub-0.2.2.dist-info/LICENSE
tepub-0.2.2.dist-info/METADATA
tepub-0.2.2.dist-info/WHEEL
tepub-0.2.2.dist-info/entry_points.txt
tepub-0.2.2.dist-info/top_level.txt
tepub-0.2.2.dist-info/RECORD
