Metadata-Version: 2.1
Name: tepub
Version: 0.2.2
Summary: TEPUB - Tools for EPUB: A comprehensive toolkit for EPUB processing including translation, audiobook generation, and export
Author-email: Xiaolai Li <xiaolaidev@gmail.com>
License: MIT
Project-URL: Homepage, https://github.com/xiaolai/tepub
Project-URL: Repository, https://github.com/xiaolai/tepub
Project-URL: Issues, https://github.com/xiaolai/tepub/issues
Project-URL: Changelog, https://github.com/xiaolai/tepub/blob/main/CHANGELOG.md
Keywords: epub,translation,audiobook,tts,ebook,nlp,i18n
Classifier: Development Status :: 4 - Beta
Classifier: Intended Audience :: Developers
Classifier: Intended Audience :: End Users/Desktop
Classifier: Operating System :: OS Independent
Classifier: Programming Language :: Python :: 3
Classifier: Programming Language :: Python :: 3.10
Classifier: Programming Language :: Python :: 3.11
Classifier: Programming Language :: Python :: 3.12
Classifier: Topic :: Multimedia :: Sound/Audio :: Speech
Classifier: Topic :: Software Development :: Libraries :: Python Modules
Classifier: Topic :: Text Processing :: Markup :: XML
Classifier: Topic :: Utilities
Requires-Python: >=3.10
License-File: LICENSE
Requires-Dist: Pillow>=10.2
Requires-Dist: cjk-text-formatter>=1.1.0
Requires-Dist: click>=8.1
Requires-Dist: ebooklib>=0.18
Requires-Dist: edge-tts>=6.1
Requires-Dist: langdetect>=1.0.9
Requires-Dist: lxml>=5.0
Requires-Dist: mutagen>=1.47
Requires-Dist: nltk>=3.9
Requires-Dist: openai>=1.0
Requires-Dist: portalocker>=3.0
Requires-Dist: pydantic>=2.6
Requires-Dist: pydub>=0.25
Requires-Dist: requests>=2.31
Requires-Dist: rich>=13.7
Provides-Extra: dev
Requires-Dist: pytest>=8.3; extra == "dev"
Requires-Dist: pytest-cov>=4.1; extra == "dev"
Requires-Dist: ruff>=0.5; extra == "dev"
Requires-Dist: black>=24.4; extra == "dev"
